anywherepython/__init__.py
anywherepython/anywherepython.py
anywherepython-0.0.2.dist-info/LICENSE
anywherepython-0.0.2.dist-info/METADATA
anywherepython-0.0.2.dist-info/WHEEL
anywherepython-0.0.2.dist-info/top_level.txt
anywherepython-0.0.2.dist-info/RECORD
