Metadata-Version: 2.1
Name: anywherepython
Version: 0.0.2
Summary: Python library for interacting with the pythonanywhere API!
Home-page: https://github.com/r3ap3rpy/anywherepython
Author: Szabó Dániel Ernő
Author-email: r3ap3rpy@gmail.com
License: MIT
Platform: UNKNOWN
Classifier: Programming Language :: Python :: 3
Classifier: License :: OSI Approved :: MIT License
Classifier: Operating System :: OS Independent
Requires-Dist: requests
